simpliflow/__init__.py
simpliflow/smartagents.py
simpliflow-0.2.1.dist-info/licenses/LICENSE
simpliflow-0.2.1.dist-info/WHEEL
simpliflow-0.2.1.dist-info/METADATA
simpliflow-0.2.1.dist-info/RECORD
