Metadata-Version: 2.4
Name: simpliflow
Version: 0.2.1
Summary: simpliflow:  An Open Source Modular Framework to quickly create, deploy, orchestrate Generative AI Agents and Agentic workflows and integrate into business applications.
Author-email: Deven Panchal <devenrpanchal@gmail.com>
Requires-Python: >=3.8
Classifier: Programming Language :: Python :: 3
Classifier: License :: OSI Approved :: Apache Software License
Classifier: Operating System :: OS Independent
License-File: LICENSE
Requires-Dist: litellm
Requires-Dist: anthropic
Requires-Dist: qiskit
Requires-Dist: matplotlib
Requires-Dist: qiskit-ibm-runtime
Requires-Dist: python-dotenv
Requires-Dist: requests
Requires-Dist: openai
Requires-Dist: cohere
Project-URL: Documentation, https://github.com/DevenPanchal/simpliflow-usage
Project-URL: Homepage, https://devenpanchal.github.io/simpliflow-website/
